dlvh/__init__.py
dlvh/__main__.py
dlvh-1.0.2.dist-info/entry_points.txt
dlvh-1.0.2.dist-info/LICENSE
dlvh-1.0.2.dist-info/WHEEL
dlvh-1.0.2.dist-info/METADATA
dlvh-1.0.2.dist-info/RECORD
