Metadata-Version: 2.1
Name: dlvh
Version: 1.0.2
Summary: Context-aware video downloader
Keywords: scripts,commandline
Author-email: Johannes Krattenmacher <dlvh@dev.krateng.ch>
Requires-Python: >=3.6
Classifier: Programming Language :: Python :: 3
Classifier: License :: OSI Approved :: GNU General Public License v3 (GPLv3)
Classifier: Operating System :: OS Independent
Requires-Dist: yt-dlp
Requires-Dist: appdirs
Requires-Dist: doreah
Project-URL: repository, https://github.com/krateng/dlvh
